sap/__init__.py
sap/cf_logging/__init__.py
sap/cf_logging/defaults.py
sap/cf_logging/core/__init__.py
sap/cf_logging/core/constants.py
sap/cf_logging/core/context.py
sap/cf_logging/core/framework.py
sap/cf_logging/core/request_reader.py
sap/cf_logging/core/response_reader.py
sap/cf_logging/django_logging/__init__.py
sap/cf_logging/django_logging/context.py
sap/cf_logging/django_logging/request_reader.py
sap/cf_logging/django_logging/response_reader.py
sap/cf_logging/falcon_logging/__init__.py
sap/cf_logging/falcon_logging/context.py
sap/cf_logging/falcon_logging/request_reader.py
sap/cf_logging/falcon_logging/response_reader.py
sap/cf_logging/flask_logging/__init__.py
sap/cf_logging/flask_logging/context.py
sap/cf_logging/flask_logging/request_reader.py
sap/cf_logging/flask_logging/response_reader.py
sap/cf_logging/formatters/__init__.py
sap/cf_logging/formatters/json_formatter.py
sap/cf_logging/formatters/stacktrace_formatter.py
sap/cf_logging/job_logging/__init__.py
sap/cf_logging/job_logging/context.py
sap/cf_logging/job_logging/framework.py
sap/cf_logging/record/__init__.py
sap/cf_logging/record/application_info.py
sap/cf_logging/record/request_log_record.py
sap/cf_logging/record/simple_log_record.py
sap/cf_logging/record/util.py
sap/cf_logging/sanic_logging/__init__.py
sap/cf_logging/sanic_logging/context.py
sap/cf_logging/sanic_logging/request_reader.py
sap/cf_logging/sanic_logging/response_reader.py
sap_cf_logging-4.2.7.dist-info/LICENSE
sap_cf_logging-4.2.7.dist-info/METADATA
sap_cf_logging-4.2.7.dist-info/WHEEL
sap_cf_logging-4.2.7.dist-info/top_level.txt
sap_cf_logging-4.2.7.dist-info/RECORD
